Metadata-Version: 2.1
Name: django-model-snapshot-diff
Version: 1.0.1
Summary: Django model snapshot difference
Home-page: https://github.com/xelaxela13/django-model-snapshot-diff
Author: xelaxela13
Author-email: xelaxela13@gmail.com
License: MIT
Keywords: make django model snapshot with relations get difference
Platform: UNKNOWN
Classifier: Development Status :: 4 - Beta
Classifier: License :: OSI Approved :: MIT License
Classifier: Programming Language :: Python
Classifier: Programming Language :: Python :: 3.5
Classifier: Programming Language :: Python :: 3.6
Classifier: Programming Language :: Python :: 3.7
Classifier: Programming Language :: Python :: 3.8
Classifier: Programming Language :: Python :: 3.9
Classifier: Framework :: Django
Classifier: Framework :: Django :: 2.0
Classifier: Framework :: Django :: 2.1
Classifier: Framework :: Django :: 2.2
Classifier: Framework :: Django :: 3.0
Classifier: Framework :: Django :: 3.1
